managerdb/__init__.py
managerdb/database_manager.py
managerdb/py.typed
managerdb-0.0.2.dist-info/METADATA
managerdb-0.0.2.dist-info/WHEEL
managerdb-0.0.2.dist-info/licenses/LICENSE
managerdb-0.0.2.dist-info/RECORD
