Metadata-Version: 2.4
Name: ManagerDB
Version: 0.0.2
Summary: Database Manager
Author-email: GameRoMan <gameromandev@gmail.com>
License: MIT
License-File: LICENSE
Keywords: database,db,manager,sql,sqlite,tool,tools
Classifier: License :: OSI Approved :: MIT License
Classifier: Programming Language :: Python :: 3
Classifier: Programming Language :: Python :: 3.10
Classifier: Programming Language :: Python :: 3.11
Classifier: Programming Language :: Python :: 3.12
Classifier: Programming Language :: Python :: 3.13
Requires-Python: >=3.10
